state_chain.py
state_chain-1.4.0.dist-info/LICENSE
state_chain-1.4.0.dist-info/METADATA
state_chain-1.4.0.dist-info/WHEEL
state_chain-1.4.0.dist-info/top_level.txt
state_chain-1.4.0.dist-info/RECORD
