Metadata-Version: 2.1
Name: state-chain
Version: 1.4.0
Summary: Model algorithms as a list of functions operating on a shared state dict.
Home-page: https://state-chain-py.readthedocs.io/
Author: Chad Whitacre et al.
Author-email: team@aspen.io
License: UNKNOWN
Platform: UNKNOWN
Classifier: Development Status :: 5 - Production/Stable
Classifier: Intended Audience :: Developers
Classifier: License :: OSI Approved :: MIT License
Classifier: Operating System :: OS Independent
Classifier: Programming Language :: Python :: 3
Classifier: Topic :: Software Development :: Libraries :: Python Modules
Requires-Dist: dependency-injection (>=1.2.0)
